near_ai_agent/__init__.py
near_ai_agent/agent.py
near_ai_agent/cli.py
near_ai_agent/environment.py
near_ai_agent/tasks.py
near_ai_agent-1.0.0a4.dist-info/METADATA
near_ai_agent-1.0.0a4.dist-info/WHEEL
near_ai_agent-1.0.0a4.dist-info/entry_points.txt
near_ai_agent-1.0.0a4.dist-info/top_level.txt
near_ai_agent-1.0.0a4.dist-info/RECORD
