Metadata-Version: 2.1
Name: near_ai_agent
Version: 1.0.0a4
Summary: A Python package to build AI agents on NEAR Protocol.
Home-page: https://github.com/joe-rlo/near_ai_agent
Author: Joe Spano
Author-email: community@near.dev
Classifier: Programming Language :: Python :: 3
Classifier: License :: OSI Approved :: MIT License
Classifier: Operating System :: OS Independent
Requires-Python: >=3.7
Requires-Dist: requests>=2.25.1
Requires-Dist: typing-extensions>=3.7.4
Requires-Dist: python-json-logger>=2.0.0
Provides-Extra: dev
Requires-Dist: pytest>=6.0; extra == "dev"
Requires-Dist: black>=21.0; extra == "dev"
Requires-Dist: isort>=5.0; extra == "dev"
Requires-Dist: mypy>=0.900; extra == "dev"
